falcon_apispec/__init__.py
falcon_apispec/falcon_plugin.py
falcon_apispec/version.py
falcon_apispec-0.4.0.dist-info/LICENSE
falcon_apispec-0.4.0.dist-info/METADATA
falcon_apispec-0.4.0.dist-info/WHEEL
falcon_apispec-0.4.0.dist-info/top_level.txt
falcon_apispec-0.4.0.dist-info/RECORD
