Metadata-Version: 2.1
Name: falcon-apispec
Version: 0.4.0
Summary: Falcon plugin for apispec documentation generator.
Home-page: https://github.com/alysivji/falcon-apispec
Author: Aly Sivji
Author-email: alysivji@gmail.com
License: UNKNOWN
Project-URL: Funding, https://falconframework.org/#sectionSupportFalconDevelopment
Project-URL: Source, https://github.com/alysivji/falcon-apispec
Project-URL: Tracker, https://github.com/alysivji/falcon-apispec/issues
Keywords: falcon apispec swagger openapi specification documentation spec rest api
Platform: UNKNOWN
Classifier: Intended Audience :: Developers
Classifier: License :: OSI Approved :: MIT License
Classifier: Natural Language :: English
Classifier: Programming Language :: Python :: 3.5
Classifier: Programming Language :: Python :: 3.6
Classifier: Programming Language :: Python :: 3.7
